README.rst
setup.py
osmoapi/__init__.py
osmoapi/osmoapi.py
osmoapi/test_osmoapi.py
osmoapi.egg-info/PKG-INFO
osmoapi.egg-info/SOURCES.txt
osmoapi.egg-info/dependency_links.txt
osmoapi.egg-info/entry_points.txt
osmoapi.egg-info/not-zip-safe
osmoapi.egg-info/requires.txt
osmoapi.egg-info/top_level.txt