Metadata-Version: 1.1
Name: osmoapi
Version: 0.1
Summary: OpenStreetMap OAuth API
Home-page: https://github.com/cleder/osmoapi
Author: Christian Ledermann
Author-email: christian.ledermann@gmail.com
License: LGPL
Keywords: osm OpenStreetMap api oauth
Platform: UNKNOWN
Classifier: Topic :: Scientific/Engineering :: GIS
Classifier: Programming Language :: Python
Classifier: Programming Language :: Python :: 2
Classifier: Programming Language :: Python :: 2.7
Classifier: Programming Language :: Python :: 3
Classifier: Programming Language :: Python :: 3.3
Classifier: Programming Language :: Python :: 3.4
Classifier: Programming Language :: Python :: 3.5
Classifier: Intended Audience :: Developers
Classifier: License :: OSI Approved :: GNU Library or Lesser General Public License (LGPL)
Classifier: Development Status :: 3 - Alpha
Classifier: Operating System :: OS Independent
